hideme_gilltick/__init__.py
hideme_gilltick/hideme_gilltrick.py
hideme_gilltrick-0.0.3.dist-info/METADATA
hideme_gilltrick-0.0.3.dist-info/WHEEL
hideme_gilltrick-0.0.3.dist-info/top_level.txt
hideme_gilltrick-0.0.3.dist-info/RECORD
